[
    { "word": "परिवार", "translation": "family", "audio": "parivaar.mp3" },
    { "word": "माँ", "translation": "mother", "audio": "maa.mp3" },
    { "word": "पिता", "translation": "father", "audio": "pita.mp3" },
    { "word": "दोस्त", "translation": "friends", "audio": "dost.mp3" },
    { "word": "दोस्ती", "translation": "friendship", "audio": "dosti.mp3" },
    { "word": "प्यार", "translation": "love", "audio": "pyaar.mp3" },
    { "word": "परिचित", "translation": "acquaintances", "audio": "parichit.mp3" },

    { "word": "सूर्य", "translation": "sun", "audio": "surya.mp3" },
    { "word": "चाँद", "translation": "moon", "audio": "chaand.mp3" },
    { "word": "बारिश", "translation": "rain", "audio": "barish.mp3" },

    { "word": "पानी", "translation": "water", "audio": "paani.mp3" },
    { "word": "भोजन", "translation": "food", "audio": "bhojan.mp3" },
    { "word": "फल", "translation": "fruit", "audio": "phal.mp3" },

    { "word": "रुपया", "translation": "money", "audio": "rupaya.mp3" },

    { "word": "घर", "translation": "house", "audio": "ghar.mp3" },
    { "word": "सड़क", "translation": "street", "audio": "sadak.mp3" },
    { "word": "शहर", "translation": "city", "audio": "shahar.mp3" },

    { "word":	"विद्यालय",	"translation":	"school",	"audio":	"vidyalaya.mp3"	},
    { "word":	"छात्र",	"translation":	"student",	"audio":	"chhatra.mp3"	},
    { "word": "किताब", "translation": "book", "audio": "kitaab.mp3" },

    { "word": "संगीत", "translation": "music", "audio": "sangeet.mp3" },

    { "word": "समय",	"translation":	"time",	"audio":	"samay.mp3"	},
    { "word":	"दिन",	"translation":	"day",	"audio":	"din.mp3"	},
    { "word":	"सप्ताह",	"translation":	"week",	"audio":	"saptah.mp3"	},
    { "word":	"महीना",	"translation":"month",	"audio":	"mahina.mp3"	},

    { "word": "मैं", "translation": "I", "audio": "main.mp3" },
    { "word": "आप", "translation": "you (formal)", "audio": "aap.mp3" },
    { "word": "तुम", "translation": "you (informal)", "audio": "tum.mp3" },
    { "word": "वह", "translation": "he", "audio": "vah.mp3" },
    { "word": "वह", "translation": "she", "audio": "vah.mp3" },
    { "word": "हम", "translation": "we", "audio": "hum.mp3" },
    { "word": "वे", "translation": "they", "audio": "ve.mp3" },

    { "word": "हरा", "translation": "green", "audio": "hara.mp3" },
    { "word": "नीला", "translation": "blue", "audio": "neela.mp3" },
    { "word": "लाल", "translation": "red", "audio": "laal.mp3" },
    { "word": "पीला", "translation": "yellow", "audio": "peela.mp3" },
    { "word": "काला", "translation": "black", "audio": "kaala.mp3" },
    { "word": "सफेद", "translation": "white", "audio": "safed.mp3" },
    { "word": "भूरा", "translation": "brown", "audio": "bhoora.mp3" },
    { "word": "धूसर", "translation": "gray", "audio": "dhusar.mp3" },

    { "word": "लिखना", "translation": "to write", "audio": "likhna.mp3" },
    { "word": "बोलना", "translation": "to speak", "audio": "bolna.mp3" },
    { "word": "सुनना", "translation": "to listen", "audio": "sunna.mp3" },
    { "word": "सुनना", "translation": "to hear", "audio": "sunna.mp3" },
    { "word": "सोचना", "translation": "to think", "audio": "sochna.mp3" },
    { "word": "चाहना", "translation": "to want", "audio": "chahna.mp3" },
    { "word": "चलना", "translation": "to walk", "audio": "chalna.mp3" },
    { "word": "भागना", "translation": "to run", "audio": "bhagna.mp3" },
    { "word": "कहना", "translation": "to say", "audio": "kehna.mp3" },
    { "word": "बताना", "translation": "to tell", "audio": "batana.mp3" },
    { "word": "जानना", "translation": "to know", "audio": "jaanna.mp3" },

    { "word": "बिल्ली", "translation": "cat", "audio": "billi.mp3" },
    { "word": "कुत्ता", "translation": "dog", "audio": "kutta.mp3" },
    { "word": "पक्षी", "translation": "bird", "audio": "pakshi.mp3" },
    { "word": "गाय", "translation": "cow", "audio": "gaay.mp3" },
    { "word": "भेड़", "translation": "sheep", "audio": "bhed.mp3" },
    { "word": "बकरी", "translation": "goat", "audio": "bakri.mp3" },
    { "word": "घोड़ा", "translation": "horse", "audio": "ghoda.mp3" },
    { "word": "हाथी", "translation": "elephant", "audio": "haathi.mp3" },
    { "word": "मछली", "translation": "fish", "audio": "machhli.mp3" },
    { "word": "सुअर", "translation": "pig", "audio": "suar.mp3" },
    { "word": "मुर्गी", "translation": "chicken", "audio": "murgi.mp3" },

    { "word": "एक", "translation": "one", "audio": "ek.mp3" },
    { "word": "दो", "translation": "two", "audio": "do.mp3" },
    { "word": "तीन", "translation": "three", "audio": "teen.mp3" },
    { "word": "चार", "translation": "four", "audio": "chaar.mp3" },
    { "word": "पांच", "translation": "five", "audio": "paanch.mp3" },
    { "word": "छह", "translation": "six", "audio": "chhah.mp3" },
    { "word": "सात", "translation": "seven", "audio": "saat.mp3" },
    { "word": "आठ", "translation": "eight", "audio": "aath.mp3" },
    { "word": "नौ", "translation": "nine", "audio": "nau.mp3" },
    { "word": "दस", "translation": "ten", "audio": "das.mp3" },

    { "word": "बीस", "translation": "twenty", "audio": "bees.mp3" },
    { "word": "तीस", "translation": "thirty", "audio": "tees.mp3" },
    { "word": "चालीस", "translation": "forty", "audio": "chalees.mp3" },
    { "word": "पचास", "translation": "fifty", "audio": "pachaas.mp3" },
    { "word": "साठ", "translation": "sixty", "audio": "saath.mp3" },
    { "word": "सत्तर", "translation": "seventy", "audio": "sattar.mp3" },
    { "word": "अस्सी", "translation": "eighty", "audio": "assi.mp3" },
    { "word": "नब्बे", "translation": "ninety", "audio": "nabbe.mp3" },
    { "word": "सौ", "translation": "one hundred", "audio": "sau.mp3" }
]
